{
  "usn": 292197,
  "nickname": "RURU",
  "total_damage": 0,
  "teams": [
    {
      "damage": 2343248063,
      "units": [
        {
          "slot": 1,
          "tid": 451105,
          "combat": 173794
        },
        {
          "slot": 2,
          "tid": 327202,
          "combat": 135247
        },
        {
          "slot": 3,
          "tid": 129004,
          "combat": 120955
        },
        {
          "slot": 4,
          "tid": 451402,
          "combat": 142607
        },
        {
          "slot": 5,
          "tid": 319401,
          "combat": 131514
        }
      ]
    },
    {
      "damage": 3003288960,
      "units": [
        {
          "slot": 1,
          "tid": 328403,
          "combat": 124014
        },
        {
          "slot": 2,
          "tid": 357003,
          "combat": 119925
        },
        {
          "slot": 3,
          "tid": 235211,
          "combat": 177211
        },
        {
          "slot": 4,
          "tid": 328301,
          "combat": 94874
        },
        {
          "slot": 5,
          "tid": 328103,
          "combat": 160920
        }
      ]
    },
    {
      "damage": 5067825726,
      "units": [
        {
          "slot": 1,
          "tid": 447104,
          "combat": 158417
        },
        {
          "slot": 2,
          "tid": 422306,
          "combat": 169088
        },
        {
          "slot": 3,
          "tid": 201604,
          "combat": 167814
        },
        {
          "slot": 4,
          "tid": 331601,
          "combat": 121573
        },
        {
          "slot": 5,
          "tid": 207501,
          "combat": 145360
        }
      ]
    },
    {
      "damage": 6459423943,
      "units": [
        {
          "slot": 1,
          "tid": 583501,
          "combat": 153016
        },
        {
          "slot": 2,
          "tid": 433009,
          "combat": 149850
        },
        {
          "slot": 3,
          "tid": 451303,
          "combat": 148201
        },
        {
          "slot": 4,
          "tid": 583401,
          "combat": 137097
        },
        {
          "slot": 5,
          "tid": 217008,
          "combat": 160715
        }
      ]
    },
    {
      "damage": 9417750273,
      "units": [
        {
          "slot": 1,
          "tid": 301701,
          "combat": 143958
        },
        {
          "slot": 2,
          "tid": 426204,
          "combat": 150597
        },
        {
          "slot": 3,
          "tid": 235504,
          "combat": 148121
        },
        {
          "slot": 4,
          "tid": 235404,
          "combat": 143765
        },
        {
          "slot": 5,
          "tid": 422502,
          "combat": 161624
        }
      ]
    }
  ]
}
