{
  "usn": 3731304,
  "nickname": "ENDY",
  "total_damage": 0,
  "teams": [
    {
      "damage": 3531505851,
      "units": [
        {
          "slot": 1,
          "tid": 343111,
          "combat": 110718
        },
        {
          "slot": 2,
          "tid": 360001,
          "combat": 142882
        },
        {
          "slot": 3,
          "tid": 101804,
          "combat": 178462
        },
        {
          "slot": 4,
          "tid": 451505,
          "combat": 169942
        },
        {
          "slot": 5,
          "tid": 360103,
          "combat": 134596
        }
      ]
    },
    {
      "damage": 2988126083,
      "units": [
        {
          "slot": 1,
          "tid": 328111,
          "combat": 192473
        },
        {
          "slot": 2,
          "tid": 328304,
          "combat": 140039
        },
        {
          "slot": 3,
          "tid": 328404,
          "combat": 147400
        },
        {
          "slot": 4,
          "tid": 357001,
          "combat": 138460
        },
        {
          "slot": 5,
          "tid": 235211,
          "combat": 172221
        }
      ]
    },
    {
      "damage": 5052520230,
      "units": [
        {
          "slot": 1,
          "tid": 201608,
          "combat": 199545
        },
        {
          "slot": 2,
          "tid": 422307,
          "combat": 172403
        },
        {
          "slot": 3,
          "tid": 447106,
          "combat": 171919
        },
        {
          "slot": 4,
          "tid": 207504,
          "combat": 169169
        },
        {
          "slot": 5,
          "tid": 116204,
          "combat": 166799
        }
      ]
    },
    {
      "damage": 7282682379,
      "units": [
        {
          "slot": 1,
          "tid": 451307,
          "combat": 173311
        },
        {
          "slot": 2,
          "tid": 433010,
          "combat": 163608
        },
        {
          "slot": 3,
          "tid": 583504,
          "combat": 172333
        },
        {
          "slot": 4,
          "tid": 583401,
          "combat": 130277
        },
        {
          "slot": 5,
          "tid": 217011,
          "combat": 181014
        }
      ]
    },
    {
      "damage": 11202017628,
      "units": [
        {
          "slot": 1,
          "tid": 235409,
          "combat": 170019
        },
        {
          "slot": 2,
          "tid": 422508,
          "combat": 177384
        },
        {
          "slot": 3,
          "tid": 426204,
          "combat": 166526
        },
        {
          "slot": 4,
          "tid": 235504,
          "combat": 157393
        },
        {
          "slot": 5,
          "tid": 301711,
          "combat": 195539
        }
      ]
    }
  ]
}
