{
  "usn": 55064,
  "nickname": "花弱弱",
  "total_damage": 35281519179,
  "teams": [
    {
      "damage": 3334348107,
      "units": [
        {
          "slot": 1,
          "tid": 101805,
          "combat": 166005
        },
        {
          "slot": 2,
          "tid": 360001,
          "combat": 113505
        },
        {
          "slot": 3,
          "tid": 447105,
          "combat": 178839
        },
        {
          "slot": 4,
          "tid": 343111,
          "combat": 97185
        },
        {
          "slot": 5,
          "tid": 360101,
          "combat": 76352
        }
      ]
    },
    {
      "damage": 5789371762,
      "units": [
        {
          "slot": 1,
          "tid": 201607,
          "combat": 195054
        },
        {
          "slot": 2,
          "tid": 422306,
          "combat": 170050
        },
        {
          "slot": 3,
          "tid": 235211,
          "combat": 184939
        },
        {
          "slot": 4,
          "tid": 207504,
          "combat": 181224
        },
        {
          "slot": 5,
          "tid": 331602,
          "combat": 127743
        }
      ]
    },
    {
      "damage": 13471371277,
      "units": [
        {
          "slot": 1,
          "tid": 301711,
          "combat": 195331
        },
        {
          "slot": 2,
          "tid": 235504,
          "combat": 147137
        },
        {
          "slot": 3,
          "tid": 426205,
          "combat": 169944
        },
        {
          "slot": 4,
          "tid": 422511,
          "combat": 200441
        },
        {
          "slot": 5,
          "tid": 235408,
          "combat": 167803
        }
      ]
    },
    {
      "damage": 8054639561,
      "units": [
        {
          "slot": 1,
          "tid": 433005,
          "combat": 162088
        },
        {
          "slot": 2,
          "tid": 451511,
          "combat": 195610
        },
        {
          "slot": 3,
          "tid": 451304,
          "combat": 159050
        },
        {
          "slot": 4,
          "tid": 583505,
          "combat": 174014
        },
        {
          "slot": 5,
          "tid": 217011,
          "combat": 175436
        }
      ]
    },
    {
      "damage": 3398209001,
      "units": [
        {
          "slot": 1,
          "tid": 328111,
          "combat": 160699
        },
        {
          "slot": 2,
          "tid": 451111,
          "combat": 193418
        },
        {
          "slot": 3,
          "tid": 331506,
          "combat": 153952
        },
        {
          "slot": 4,
          "tid": 328401,
          "combat": 133065
        },
        {
          "slot": 5,
          "tid": 116205,
          "combat": 176589
        }
      ]
    }
  ]
}
