{
  "usn": 7603172,
  "nickname": "七夜",
  "total_damage": 0,
  "teams": [
    {
      "damage": 359116617,
      "units": [
        {
          "slot": 1,
          "tid": 422306,
          "combat": 666115
        },
        {
          "slot": 2,
          "tid": 422511,
          "combat": 855709
        },
        {
          "slot": 3,
          "tid": 451311,
          "combat": 730009
        },
        {
          "slot": 4,
          "tid": 426205,
          "combat": 682348
        },
        {
          "slot": 5,
          "tid": 331603,
          "combat": 391493
        }
      ]
    }
  ]
}
