{
  "usn": 10856693,
  "nickname": "ILCHOL",
  "total_damage": 44043156567,
  "teams": [
    {
      "damage": 14723882121,
      "units": [
        {
          "slot": 1,
          "tid": 301711,
          "combat": 205693
        },
        {
          "slot": 2,
          "tid": 426211,
          "combat": 188101
        },
        {
          "slot": 3,
          "tid": 235511,
          "combat": 176353
        },
        {
          "slot": 4,
          "tid": 422511,
          "combat": 222140
        },
        {
          "slot": 5,
          "tid": 235411,
          "combat": 163798
        }
      ]
    },
    {
      "damage": 4355287862,
      "units": [
        {
          "slot": 1,
          "tid": 258311,
          "combat": 191373
        },
        {
          "slot": 2,
          "tid": 327111,
          "combat": 178690
        },
        {
          "slot": 3,
          "tid": 119211,
          "combat": 182321
        },
        {
          "slot": 4,
          "tid": 207410,
          "combat": 178444
        },
        {
          "slot": 5,
          "tid": 110111,
          "combat": 190151
        }
      ]
    },
    {
      "damage": 6912281518,
      "units": [
        {
          "slot": 1,
          "tid": 360007,
          "combat": 163253
        },
        {
          "slot": 2,
          "tid": 201611,
          "combat": 216046
        },
        {
          "slot": 3,
          "tid": 447111,
          "combat": 216139
        },
        {
          "slot": 4,
          "tid": 357008,
          "combat": 180273
        },
        {
          "slot": 5,
          "tid": 360103,
          "combat": 152845
        }
      ]
    },
    {
      "damage": 9297412512,
      "units": [
        {
          "slot": 1,
          "tid": 433011,
          "combat": 172246
        },
        {
          "slot": 2,
          "tid": 451311,
          "combat": 187792
        },
        {
          "slot": 3,
          "tid": 583511,
          "combat": 178430
        },
        {
          "slot": 4,
          "tid": 583411,
          "combat": 169436
        },
        {
          "slot": 5,
          "tid": 217011,
          "combat": 191991
        }
      ]
    },
    {
      "damage": 7520713083,
      "units": [
        {
          "slot": 1,
          "tid": 328111,
          "combat": 164751
        },
        {
          "slot": 2,
          "tid": 451507,
          "combat": 176359
        },
        {
          "slot": 3,
          "tid": 422311,
          "combat": 203820
        },
        {
          "slot": 4,
          "tid": 235211,
          "combat": 179680
        },
        {
          "slot": 5,
          "tid": 331611,
          "combat": 166433
        }
      ]
    }
  ]
}
