{
  "usn": 1427667,
  "nickname": "カプリス",
  "total_damage": 0,
  "teams": [
    {
      "damage": 359116617,
      "units": [
        {
          "slot": 1,
          "tid": 119211,
          "combat": 960951
        },
        {
          "slot": 2,
          "tid": 422305,
          "combat": 1044823
        },
        {
          "slot": 3,
          "tid": 423410,
          "combat": 1263786
        },
        {
          "slot": 4,
          "tid": 110111,
          "combat": 950898
        },
        {
          "slot": 5,
          "tid": 207402,
          "combat": 656002
        }
      ]
    }
  ]
}
