{
  "usn": 15012712,
  "nickname": "SORAKO",
  "total_damage": 53259184857,
  "teams": [
    {
      "damage": 7902941259,
      "units": [
        {
          "slot": 1,
          "tid": 360011,
          "combat": 184974
        },
        {
          "slot": 2,
          "tid": 360103,
          "combat": 144617
        },
        {
          "slot": 3,
          "tid": 201611,
          "combat": 186853
        },
        {
          "slot": 4,
          "tid": 357011,
          "combat": 214062
        },
        {
          "slot": 5,
          "tid": 328411,
          "combat": 185194
        }
      ]
    },
    {
      "damage": 11312328744,
      "units": [
        {
          "slot": 1,
          "tid": 217011,
          "combat": 171852
        },
        {
          "slot": 2,
          "tid": 331611,
          "combat": 206746
        },
        {
          "slot": 3,
          "tid": 235211,
          "combat": 170800
        },
        {
          "slot": 4,
          "tid": 451311,
          "combat": 212677
        },
        {
          "slot": 5,
          "tid": 433011,
          "combat": 173944
        }
      ]
    },
    {
      "damage": 7623687602,
      "units": [
        {
          "slot": 1,
          "tid": 328111,
          "combat": 176649
        },
        {
          "slot": 2,
          "tid": 331511,
          "combat": 165737
        },
        {
          "slot": 3,
          "tid": 583511,
          "combat": 206586
        },
        {
          "slot": 4,
          "tid": 583411,
          "combat": 200867
        },
        {
          "slot": 5,
          "tid": 319411,
          "combat": 182374
        }
      ]
    },
    {
      "damage": 7495209328,
      "units": [
        {
          "slot": 1,
          "tid": 203211,
          "combat": 172413
        },
        {
          "slot": 2,
          "tid": 110211,
          "combat": 159753
        },
        {
          "slot": 3,
          "tid": 422311,
          "combat": 216023
        },
        {
          "slot": 4,
          "tid": 327211,
          "combat": 179832
        },
        {
          "slot": 5,
          "tid": 207507,
          "combat": 171632
        }
      ]
    },
    {
      "damage": 17691438453,
      "units": [
        {
          "slot": 1,
          "tid": 235411,
          "combat": 166543
        },
        {
          "slot": 2,
          "tid": 422511,
          "combat": 229062
        },
        {
          "slot": 3,
          "tid": 301711,
          "combat": 166064
        },
        {
          "slot": 4,
          "tid": 426211,
          "combat": 225002
        },
        {
          "slot": 5,
          "tid": 235509,
          "combat": 163842
        }
      ]
    }
  ]
}
