{
  "usn": 1818119,
  "nickname": "めいでんさん",
  "total_damage": 0,
  "teams": [
    {
      "damage": 3204086444,
      "units": [
        {
          "slot": 1,
          "tid": 451111,
          "combat": 185555
        },
        {
          "slot": 2,
          "tid": 327211,
          "combat": 185395
        },
        {
          "slot": 3,
          "tid": 447111,
          "combat": 208365
        },
        {
          "slot": 4,
          "tid": 327011,
          "combat": 161280
        },
        {
          "slot": 5,
          "tid": 116209,
          "combat": 183380
        }
      ]
    },
    {
      "damage": 3811660813,
      "units": [
        {
          "slot": 1,
          "tid": 328111,
          "combat": 177750
        },
        {
          "slot": 2,
          "tid": 101808,
          "combat": 195213
        },
        {
          "slot": 3,
          "tid": 360101,
          "combat": 147518
        },
        {
          "slot": 4,
          "tid": 360005,
          "combat": 157395
        },
        {
          "slot": 5,
          "tid": 327111,
          "combat": 166791
        }
      ]
    },
    {
      "damage": 11752962621,
      "units": [
        {
          "slot": 1,
          "tid": 301709,
          "combat": 196086
        },
        {
          "slot": 2,
          "tid": 426204,
          "combat": 171291
        },
        {
          "slot": 3,
          "tid": 235509,
          "combat": 133094
        },
        {
          "slot": 4,
          "tid": 422511,
          "combat": 201693
        },
        {
          "slot": 5,
          "tid": 235411,
          "combat": 159239
        }
      ]
    },
    {
      "damage": 7288186537,
      "units": [
        {
          "slot": 1,
          "tid": 451509,
          "combat": 182216
        },
        {
          "slot": 2,
          "tid": 422306,
          "combat": 153412
        },
        {
          "slot": 3,
          "tid": 451307,
          "combat": 163899
        },
        {
          "slot": 4,
          "tid": 331606,
          "combat": 154078
        },
        {
          "slot": 5,
          "tid": 217011,
          "combat": 192592
        }
      ]
    },
    {
      "damage": 5211840216,
      "units": [
        {
          "slot": 1,
          "tid": 201610,
          "combat": 201553
        },
        {
          "slot": 2,
          "tid": 583504,
          "combat": 153919
        },
        {
          "slot": 3,
          "tid": 583404,
          "combat": 150642
        },
        {
          "slot": 4,
          "tid": 235211,
          "combat": 177810
        },
        {
          "slot": 5,
          "tid": 433011,
          "combat": 149201
        }
      ]
    }
  ]
}
