{
  "usn": 25176591,
  "nickname": "TESTIFY",
  "total_damage": 0,
  "teams": [
    {
      "damage": 3783815375,
      "units": [
        {
          "slot": 1,
          "tid": 343111,
          "combat": 99680
        },
        {
          "slot": 2,
          "tid": 360101,
          "combat": 140855
        },
        {
          "slot": 3,
          "tid": 235211,
          "combat": 168123
        },
        {
          "slot": 4,
          "tid": 451111,
          "combat": 221264
        },
        {
          "slot": 5,
          "tid": 360001,
          "combat": 136533
        }
      ]
    },
    {
      "damage": 6158172599,
      "units": [
        {
          "slot": 1,
          "tid": 451306,
          "combat": 156039
        },
        {
          "slot": 2,
          "tid": 433010,
          "combat": 173856
        },
        {
          "slot": 3,
          "tid": 583503,
          "combat": 145980
        },
        {
          "slot": 4,
          "tid": 319411,
          "combat": 176122
        },
        {
          "slot": 5,
          "tid": 217011,
          "combat": 171237
        }
      ]
    },
    {
      "damage": 4861406953,
      "units": [
        {
          "slot": 1,
          "tid": 201606,
          "combat": 175996
        },
        {
          "slot": 2,
          "tid": 422303,
          "combat": 152778
        },
        {
          "slot": 3,
          "tid": 319111,
          "combat": 192901
        },
        {
          "slot": 4,
          "tid": 101808,
          "combat": 184527
        },
        {
          "slot": 5,
          "tid": 327111,
          "combat": 148209
        }
      ]
    },
    {
      "damage": 3777314522,
      "units": [
        {
          "slot": 1,
          "tid": 203211,
          "combat": 155727
        },
        {
          "slot": 2,
          "tid": 327011,
          "combat": 154230
        },
        {
          "slot": 3,
          "tid": 447103,
          "combat": 148632
        },
        {
          "slot": 4,
          "tid": 327204,
          "combat": 153329
        },
        {
          "slot": 5,
          "tid": 584005,
          "combat": 186750
        }
      ]
    },
    {
      "damage": 12158612426,
      "units": [
        {
          "slot": 1,
          "tid": 235505,
          "combat": 163983
        },
        {
          "slot": 2,
          "tid": 301706,
          "combat": 185962
        },
        {
          "slot": 3,
          "tid": 426203,
          "combat": 149480
        },
        {
          "slot": 4,
          "tid": 422511,
          "combat": 192909
        },
        {
          "slot": 5,
          "tid": 235407,
          "combat": 150191
        }
      ]
    }
  ]
}
