{
  "usn": 4344084,
  "nickname": "RIZA",
  "total_damage": 0,
  "teams": [
    {
      "damage": 4258759424,
      "units": [
        {
          "slot": 1,
          "tid": 451411,
          "combat": 175837
        },
        {
          "slot": 2,
          "tid": 101810,
          "combat": 210323
        },
        {
          "slot": 3,
          "tid": 451511,
          "combat": 167317
        },
        {
          "slot": 4,
          "tid": 129011,
          "combat": 169222
        },
        {
          "slot": 5,
          "tid": 328111,
          "combat": 158894
        }
      ]
    },
    {
      "damage": 5703183961,
      "units": [
        {
          "slot": 1,
          "tid": 360002,
          "combat": 156023
        },
        {
          "slot": 2,
          "tid": 328411,
          "combat": 188417
        },
        {
          "slot": 3,
          "tid": 447111,
          "combat": 219733
        },
        {
          "slot": 4,
          "tid": 201611,
          "combat": 222431
        },
        {
          "slot": 5,
          "tid": 360101,
          "combat": 150552
        }
      ]
    },
    {
      "damage": 9139415126,
      "units": [
        {
          "slot": 1,
          "tid": 433011,
          "combat": 160514
        },
        {
          "slot": 2,
          "tid": 583511,
          "combat": 185716
        },
        {
          "slot": 3,
          "tid": 451311,
          "combat": 200710
        },
        {
          "slot": 4,
          "tid": 583411,
          "combat": 181239
        },
        {
          "slot": 5,
          "tid": 331604,
          "combat": 157633
        }
      ]
    },
    {
      "damage": 13435469472,
      "units": [
        {
          "slot": 1,
          "tid": 235411,
          "combat": 164772
        },
        {
          "slot": 2,
          "tid": 426209,
          "combat": 187276
        },
        {
          "slot": 3,
          "tid": 422511,
          "combat": 206121
        },
        {
          "slot": 4,
          "tid": 301711,
          "combat": 179206
        },
        {
          "slot": 5,
          "tid": 235511,
          "combat": 173705
        }
      ]
    },
    {
      "damage": 6477656005,
      "units": [
        {
          "slot": 1,
          "tid": 203211,
          "combat": 184300
        },
        {
          "slot": 2,
          "tid": 217011,
          "combat": 169043
        },
        {
          "slot": 3,
          "tid": 422311,
          "combat": 185119
        },
        {
          "slot": 4,
          "tid": 327211,
          "combat": 158272
        },
        {
          "slot": 5,
          "tid": 235211,
          "combat": 172834
        }
      ]
    }
  ]
}
