{
  "usn": 5230106,
  "nickname": "がぶちゃん",
  "total_damage": 46323693977,
  "teams": [
    {
      "damage": 4539722096,
      "units": [
        {
          "slot": 1,
          "tid": 258310,
          "combat": 181347
        },
        {
          "slot": 2,
          "tid": 119211,
          "combat": 184755
        },
        {
          "slot": 3,
          "tid": 423411,
          "combat": 206591
        },
        {
          "slot": 4,
          "tid": 327111,
          "combat": 167726
        },
        {
          "slot": 5,
          "tid": 207408,
          "combat": 175298
        }
      ]
    },
    {
      "damage": 6358444691,
      "units": [
        {
          "slot": 1,
          "tid": 360005,
          "combat": 165530
        },
        {
          "slot": 2,
          "tid": 328111,
          "combat": 173234
        },
        {
          "slot": 3,
          "tid": 447111,
          "combat": 199912
        },
        {
          "slot": 4,
          "tid": 357011,
          "combat": 191997
        },
        {
          "slot": 5,
          "tid": 360107,
          "combat": 157152
        }
      ]
    },
    {
      "damage": 7767812222,
      "units": [
        {
          "slot": 1,
          "tid": 433011,
          "combat": 179146
        },
        {
          "slot": 2,
          "tid": 201611,
          "combat": 201743
        },
        {
          "slot": 3,
          "tid": 583511,
          "combat": 198299
        },
        {
          "slot": 4,
          "tid": 583404,
          "combat": 165779
        },
        {
          "slot": 5,
          "tid": 235211,
          "combat": 184173
        }
      ]
    },
    {
      "damage": 10906179952,
      "units": [
        {
          "slot": 1,
          "tid": 422311,
          "combat": 207073
        },
        {
          "slot": 2,
          "tid": 451511,
          "combat": 183994
        },
        {
          "slot": 3,
          "tid": 451311,
          "combat": 199650
        },
        {
          "slot": 4,
          "tid": 217011,
          "combat": 176213
        },
        {
          "slot": 5,
          "tid": 331607,
          "combat": 173427
        }
      ]
    },
    {
      "damage": 15517955545,
      "units": [
        {
          "slot": 1,
          "tid": 301711,
          "combat": 202188
        },
        {
          "slot": 2,
          "tid": 426211,
          "combat": 219546
        },
        {
          "slot": 3,
          "tid": 235511,
          "combat": 169695
        },
        {
          "slot": 4,
          "tid": 235411,
          "combat": 177325
        },
        {
          "slot": 5,
          "tid": 422511,
          "combat": 224781
        }
      ]
    }
  ]
}
