{
  "usn": 5242299,
  "nickname": "LUKA",
  "total_damage": 0,
  "teams": [
    {
      "damage": 359116617,
      "units": [
        {
          "slot": 1,
          "tid": 451311,
          "combat": 843482
        },
        {
          "slot": 2,
          "tid": 433011,
          "combat": 822112
        },
        {
          "slot": 3,
          "tid": 422511,
          "combat": 945621
        },
        {
          "slot": 4,
          "tid": 426211,
          "combat": 940437
        },
        {
          "slot": 5,
          "tid": 235211,
          "combat": 864102
        }
      ]
    }
  ]
}
