{
  "usn": 71778773,
  "nickname": "72卍SHIN",
  "total_damage": 0,
  "teams": [
    {
      "damage": 12296473120,
      "units": [
        {
          "slot": 1,
          "tid": 422511,
          "combat": 196901
        },
        {
          "slot": 2,
          "tid": 235411,
          "combat": 184835
        },
        {
          "slot": 3,
          "tid": 235511,
          "combat": 170299
        },
        {
          "slot": 4,
          "tid": 301711,
          "combat": 190759
        },
        {
          "slot": 5,
          "tid": 426211,
          "combat": 197810
        }
      ]
    },
    {
      "damage": 7989676955,
      "units": [
        {
          "slot": 1,
          "tid": 433011,
          "combat": 168110
        },
        {
          "slot": 2,
          "tid": 583506,
          "combat": 164936
        },
        {
          "slot": 3,
          "tid": 451311,
          "combat": 185197
        },
        {
          "slot": 4,
          "tid": 451511,
          "combat": 175651
        },
        {
          "slot": 5,
          "tid": 217011,
          "combat": 201490
        }
      ]
    },
    {
      "damage": 5109647047,
      "units": [
        {
          "slot": 1,
          "tid": 201611,
          "combat": 204782
        },
        {
          "slot": 2,
          "tid": 360005,
          "combat": 164519
        },
        {
          "slot": 3,
          "tid": 447111,
          "combat": 206252
        },
        {
          "slot": 4,
          "tid": 357004,
          "combat": 153254
        },
        {
          "slot": 5,
          "tid": 360104,
          "combat": 144762
        }
      ]
    },
    {
      "damage": 5777268426,
      "units": [
        {
          "slot": 1,
          "tid": 203211,
          "combat": 167967
        },
        {
          "slot": 2,
          "tid": 207506,
          "combat": 170239
        },
        {
          "slot": 3,
          "tid": 235211,
          "combat": 174485
        },
        {
          "slot": 4,
          "tid": 422311,
          "combat": 204635
        },
        {
          "slot": 5,
          "tid": 328111,
          "combat": 162219
        }
      ]
    },
    {
      "damage": 3617741543,
      "units": [
        {
          "slot": 1,
          "tid": 119211,
          "combat": 163366
        },
        {
          "slot": 2,
          "tid": 258306,
          "combat": 164264
        },
        {
          "slot": 3,
          "tid": 423406,
          "combat": 174864
        },
        {
          "slot": 4,
          "tid": 327111,
          "combat": 164068
        },
        {
          "slot": 5,
          "tid": 207410,
          "combat": 166573
        }
      ]
    }
  ]
}
