{
  "usn": 74001277,
  "nickname": "すばしっこい幽霊",
  "total_damage": 0,
  "teams": [
    {
      "damage": 359116617,
      "units": [
        {
          "slot": 1,
          "tid": 301711,
          "combat": 1900036
        },
        {
          "slot": 2,
          "tid": 235411,
          "combat": 1577536
        },
        {
          "slot": 3,
          "tid": 422511,
          "combat": 1865947
        },
        {
          "slot": 4,
          "tid": 426211,
          "combat": 1613076
        },
        {
          "slot": 5,
          "tid": 235511,
          "combat": 1838074
        }
      ]
    }
  ]
}
