{
  "usn": 74062100,
  "nickname": "TK",
  "total_damage": 0,
  "teams": [
    {
      "damage": 359116617,
      "units": [
        {
          "slot": 1,
          "tid": 433011,
          "combat": 1056149
        },
        {
          "slot": 2,
          "tid": 422511,
          "combat": 1169713
        },
        {
          "slot": 3,
          "tid": 451311,
          "combat": 1087675
        },
        {
          "slot": 4,
          "tid": 426211,
          "combat": 1129753
        },
        {
          "slot": 5,
          "tid": 331602,
          "combat": 760198
        }
      ]
    }
  ]
}
