{
  "usn": 941054,
  "nickname": "さとかす",
  "total_damage": 0,
  "teams": [
    {
      "damage": 5085952771,
      "units": [
        {
          "slot": 1,
          "tid": 360005,
          "combat": 164856
        },
        {
          "slot": 2,
          "tid": 328111,
          "combat": 178054
        },
        {
          "slot": 3,
          "tid": 447107,
          "combat": 166043
        },
        {
          "slot": 4,
          "tid": 357004,
          "combat": 166511
        },
        {
          "slot": 5,
          "tid": 360106,
          "combat": 161606
        }
      ]
    },
    {
      "damage": 12272378228,
      "units": [
        {
          "slot": 1,
          "tid": 301711,
          "combat": 226313
        },
        {
          "slot": 2,
          "tid": 235508,
          "combat": 122044
        },
        {
          "slot": 3,
          "tid": 235411,
          "combat": 162939
        },
        {
          "slot": 4,
          "tid": 426211,
          "combat": 212912
        },
        {
          "slot": 5,
          "tid": 422511,
          "combat": 194384
        }
      ]
    },
    {
      "damage": 9727452240,
      "units": [
        {
          "slot": 1,
          "tid": 217011,
          "combat": 200302
        },
        {
          "slot": 2,
          "tid": 451507,
          "combat": 154491
        },
        {
          "slot": 3,
          "tid": 451311,
          "combat": 234926
        },
        {
          "slot": 4,
          "tid": 422311,
          "combat": 202794
        },
        {
          "slot": 5,
          "tid": 331606,
          "combat": 165257
        }
      ]
    },
    {
      "damage": 6068712079,
      "units": [
        {
          "slot": 1,
          "tid": 433011,
          "combat": 181592
        },
        {
          "slot": 2,
          "tid": 201611,
          "combat": 204111
        },
        {
          "slot": 3,
          "tid": 583504,
          "combat": 163614
        },
        {
          "slot": 4,
          "tid": 583404,
          "combat": 163057
        },
        {
          "slot": 5,
          "tid": 235211,
          "combat": 186658
        }
      ]
    },
    {
      "damage": 3611680424,
      "units": [
        {
          "slot": 1,
          "tid": 258311,
          "combat": 178469
        },
        {
          "slot": 2,
          "tid": 119211,
          "combat": 176351
        },
        {
          "slot": 3,
          "tid": 423411,
          "combat": 195338
        },
        {
          "slot": 4,
          "tid": 327111,
          "combat": 161298
        },
        {
          "slot": 5,
          "tid": 207405,
          "combat": 151888
        }
      ]
    }
  ]
}
